kneejerk/__init__.py
kneejerk/cli.py
kneejerk/image_server.py
kneejerk/data/__init__.py
kneejerk/data/saver.py
kneejerk/data/transfer.py
kneejerk/data/utils.py
kneejerk-1.0.0.dist-info/LICENSE
kneejerk-1.0.0.dist-info/METADATA
kneejerk-1.0.0.dist-info/WHEEL
kneejerk-1.0.0.dist-info/entry_points.txt
kneejerk-1.0.0.dist-info/top_level.txt
kneejerk-1.0.0.dist-info/RECORD
