Metadata-Version: 2.1
Name: kneejerk
Version: 1.0.0
Summary: A package for labelling image data with your quick, kneejerk reactions.
Home-page: https://github.com/NapsterInBlue
Author: NapsterInBlue
Author-email: NapsterInBlue@google.com
License: MIT
Platform: UNKNOWN
Requires-Dist: opencv-python
Requires-Dist: Click
Requires-Dist: matplotlib
Requires-Dist: numpy
